polybin/__init__.py
polybin/api.py
polybin/builders.py
polybin/cli.py
polybin/ico/__init__.py
polybin/ico/_core.py
polybin/mp4/__init__.py
polybin/mp4/_core.py
polybin/zip/__init__.py
polybin/zip/_core.py
tests/run_tests.py
tests/test.py
polybin-0.1.0.dist-info/METADATA
polybin-0.1.0.dist-info/WHEEL
polybin-0.1.0.dist-info/entry_points.txt
polybin-0.1.0.dist-info/top_level.txt
polybin-0.1.0.dist-info/RECORD
