Metadata-Version: 2.4
Name: polybin
Version: 0.1.0
Summary: Smash formats together. Break assumptions. Build valid chaos. A polyglot builder for ICO, MP4, and ZIP files.
Home-page: https://github.com/viodoescyber/polybin
Author: viodoescyber
License: MIT
Project-URL: Homepage, https://github.com/viodoescyber/polybin
Project-URL: Repository, https://github.com/viodoescyber/polybin
Project-URL: Issues, https://github.com/viodoescyber/polybin/issues
Classifier: Programming Language :: Python :: 3
Classifier: License :: OSI Approved :: MIT License
Classifier: Operating System :: OS Independent
Requires-Python: >=3.9
Requires-Dist: Pillow>=11.2.1
Requires-Dist: setuptools>=80.9.0
Dynamic: home-page
Dynamic: requires-python
